task_context_mcp/__init__.py
task_context_mcp/alembic/README
task_context_mcp/alembic/env.py
task_context_mcp/alembic/script.py.mako
task_context_mcp/alembic/versions/2025_12_14_1220-261b037d15fa_initial_schema.py
task_context_mcp/alembic.ini
task_context_mcp/config/__init__.py
task_context_mcp/config/logging.py
task_context_mcp/config/settings.py
task_context_mcp/database/__init__.py
task_context_mcp/database/database.py
task_context_mcp/database/migrations.py
task_context_mcp/database/models.py
task_context_mcp/main.py
task_context_mcp/models.py
task_context_mcp/server.py
task_context_mcp/tools.py
task_context_mcp-0.1.6.dist-info/WHEEL
task_context_mcp-0.1.6.dist-info/entry_points.txt
task_context_mcp-0.1.6.dist-info/METADATA
task_context_mcp-0.1.6.dist-info/RECORD
