Metadata-Version: 2.3
Name: task-context-mcp
Version: 0.1.6
Summary: MCP server for managing task contexts.
Keywords: mcp,model-context-protocol,developer-tools,fastmcp
Author: l0kifs
Author-email: l0kifs <l0kifs91@gmail.com>
License: MIT
Classifier: Development Status :: 3 - Alpha
Classifier: Intended Audience :: Developers
Classifier: License :: OSI Approved :: MIT License
Classifier: Operating System :: OS Independent
Classifier: Operating System :: Microsoft :: Windows
Classifier: Operating System :: MacOS
Classifier: Operating System :: POSIX :: Linux
Classifier: Programming Language :: Python :: 3
Classifier: Programming Language :: Python :: 3.12
Classifier: Programming Language :: Python :: 3.13
Classifier: Topic :: Software Development :: Libraries :: Python Modules
Classifier: Environment :: Plugins
Classifier: Natural Language :: English
Requires-Dist: fastmcp>=2.13.3
Requires-Dist: loguru>=0.7.3
Requires-Dist: sqlalchemy>=2.0.44
Requires-Dist: alembic>=1.17.2
Requires-Dist: pydantic>=2.12.5
Requires-Dist: pydantic-settings>=2.12.0
Maintainer: l0kifs
Maintainer-email: l0kifs <l0kifs91@gmail.com>
Requires-Python: >=3.12
Project-URL: Changelog, https://github.com/l0kifs/task-context-mcp/blob/main/CHANGELOG.md
Project-URL: Documentation, https://github.com/l0kifs/task-context-mcp/blob/main/README.md
Project-URL: Homepage, https://github.com/l0kifs/task-context-mcp
Project-URL: Issues, https://github.com/l0kifs/task-context-mcp/issues
Project-URL: Repository, https://github.com/l0kifs/task-context-mcp.git
